internal/framebuffer.v
module framebuffer(
    input clk,
    input [9:0] read_addr,
    output reg [23:0] pixel_out,

    input [9:0] write_addr,
    input [23:0] write_data,
    input write_en
);
    reg [23:0] mem [0:1023];

    always @(posedge clk) begin
        pixel_out <= mem[read_addr];

        if (write_en) begin
            mem[write_addr] <= write_data;
        end
    end

endmodule

testbenchs/framebuffer_tb.v
`timescale 1ns/1ps // <time_unit>/<time_precision

module framebuffer_tb;
    reg clk;
    reg [9:0] read_addr;
    wire [23:0] pixel_out;
    reg [9:0] write_addr;
    reg [23:0] write_data;
    reg write_en;

    framebuffer instance1(
        .clk (clk),
        .read_addr(read_addr),
        .pixel_out(pixel_out),
        .write_addr(write_addr),
        .write_data(write_data),
        .write_en(write_en)
    );

    initial clk=0;
    always #20 clk = ~clk;

    initial begin
        $dumpfile("framebuffer_tb.vcd");
        $dumpvars(0, framebuffer_tb);

        write_en = 1;

        write_addr = 10'd5;
        write_data = 24'hFF0000;

        #40;

        read_addr = 10'd5;

        #40;
// test2
        write_en = 1;

        write_addr = 10'd1023;
        write_data = 24'h0000FF;

        #40;

        read_addr = 10'd1023;

        #40;
//test3
        write_en = 1;

        write_addr = 10'd0;
        write_data = 24'hAABBCC;
        #40;

        write_en=0;
        write_data=24'h001122;
        #40;

        read_addr = 10'd0;

        #40;


        $finish;
    end


endmodule

sim/framebuffer_tb.vcd
$date
	Tue Mar 31 18:21:10 2026
$end
$version
	Icarus Verilog
$end
$timescale
	1ps
$end
$scope module framebuffer_tb $end
$var wire 24 ! pixel_out [23:0] $end
$var reg 1 " clk $end
$var reg 10 # read_addr [9:0] $end
$var reg 10 $ write_addr [9:0] $end
$var reg 24 % write_data [23:0] $end
$var reg 1 & write_en $end
$scope module instance1 $end
$var wire 1 " clk $end
$var wire 10 ' read_addr [9:0] $end
$var wire 10 ( write_addr [9:0] $end
$var wire 24 ) write_data [23:0] $end
$var wire 1 & write_en $end
$var reg 24 * pixel_out [23:0] $end
$upscope $end
$upscope $end
$enddefinitions $end
$comment Show the parameter values. $end
$dumpall
$end
#0
$dumpvars
bx *
b111111110000000000000000 )
b101 (
bx '
1&
b111111110000000000000000 %
b101 $
bx #
0"
bx !
$end
#20000
1"
#40000
0"
b101 #
b101 '
#60000
b111111110000000000000000 !
b111111110000000000000000 *
1"
#80000
0"
b11111111 %
b11111111 )
b1111111111 $
b1111111111 (
#100000
1"
#120000
0"
b1111111111 #
b1111111111 '
#140000
b11111111 !
b11111111 *
1"
#160000
0"
b101010101011101111001100 %
b101010101011101111001100 )
b0 $
b0 (
#180000
1"
#200000
0"
b1000100100010 %
b1000100100010 )
0&
#220000
1"
#240000
0"
b0 #
b0 '
#260000
b101010101011101111001100 !
b101010101011101111001100 *
1"
